LICENSE.txt
MANIFEST.in
README.rst
changelog.rst
requirements.txt
setup.py
./setup.py
evilmc/__init__.py
evilmc/evilmc.py
evilmc.egg-info/PKG-INFO
evilmc.egg-info/SOURCES.txt
evilmc.egg-info/dependency_links.txt
evilmc.egg-info/requires.txt
evilmc.egg-info/top_level.txt
evilmc/data/kepler_response_hires1.txt
tests/__init__.py
tests/test_evilmc.py