Metadata-Version: 1.1
Name: evilmc
Version: 0.26
Summary: A python version of the EVIL-MC code
Home-page: https://github.com/BoiseStatePlanetary/evilmc
Author: Brian Jackson
Author-email: bjackson@boisestate.edu
License: BSD
Download-URL: https://github.com/BoiseStatePlanetary/evilmc/archive/0.26.tar.gz
Platform: UNKNOWN
Classifier: Development Status :: 2 - Pre-Alpha
